klocker/__init__.py
klocker/exception.py
klocker/simple/__init__.py
klocker/simple/constants.py
klocker/simple/shared.py
klocker/simple/user.py
klocker/simple/locker/__init__.py
klocker/simple/locker/config.py
klocker/simple/locker/locker.py
klocker/simple/locker/private.py
klocker/simple/locker/proxy.py
klocker/simple/thread/__init__.py
klocker/simple/thread/base.py
klocker/simple/thread/config.py
klocker/simple/thread/state.py
klocker/simple/thread/thread.py
klocker/test/__init__.py
klocker/test/test.py
klocker-0.1.4.3.dist-info/licenses/LICENSE
klocker-0.1.4.3.dist-info/METADATA
klocker-0.1.4.3.dist-info/WHEEL
klocker-0.1.4.3.dist-info/top_level.txt
klocker-0.1.4.3.dist-info/RECORD
